CHANGELOG.txt
LICIENCE.txt
MANIFEST.in
README.txt
setup.py
TPreprocess/__init__.py
tpreprocessing.egg-info/PKG-INFO
tpreprocessing.egg-info/SOURCES.txt
tpreprocessing.egg-info/dependency_links.txt
tpreprocessing.egg-info/top_level.txt